changelog/__init__.py
changelog_parser-0.0.8.dist-info/LICENSE
changelog_parser-0.0.8.dist-info/METADATA
changelog_parser-0.0.8.dist-info/WHEEL
changelog_parser-0.0.8.dist-info/top_level.txt
changelog_parser-0.0.8.dist-info/RECORD
