Metadata-Version: 2.1
Name: changelog-parser
Version: 0.0.8
Summary: Parses changelog files
Author-email: Jason Stiefel <Jason.R.Stiefel@gmail.com>
License: MIT License
Project-URL: homepage, https://github.com/JasonStiefel/changelog-parser
Project-URL: changelog, https://github.com/JasonStiefel/changelog-parser/blob/main/CHANGELOG.md
Classifier: License :: OSI Approved :: MIT License
Classifier: Programming Language :: Python :: 3
Classifier: Programming Language :: Python :: 3 :: Only
Classifier: Programming Language :: Python :: 3.8
Classifier: Programming Language :: Python :: 3.9
Classifier: Programming Language :: Python :: 3.10
Classifier: Programming Language :: Python :: 3.11
Classifier: Programming Language :: Python :: 3.12
Classifier: Programming Language :: Python :: Implementation :: CPython
Classifier: Programming Language :: Python :: Implementation :: PyPy
Requires-Python: >=3.8
License-File: LICENSE
Requires-Dist: semver
Provides-Extra: test
Requires-Dist: coverage ; extra == 'test'
Requires-Dist: pylint ; extra == 'test'
Requires-Dist: pytest ; extra == 'test'
Requires-Dist: pytest-xdist ; extra == 'test'
